{"Helsinki": 26, "Vilnius": 27, "Seoul": 23, "Kuala Lumpur": 30, "Atlanta": 22, "Caracas": 29, "Rio De Janeiro": 25, "Amsterdam": 25, "Valencia": 30, "Beijing": 33, "Warsaw": 26, "Moscow": 27, "Zurich": 21, "London": 26, "Berlin": 27, "Lagos": 31, "Brussels": 27, "Munich": 16, "Cairo": 33, "Toronto": 22, "Cape Town": 16, "Mumbai": 26, "Hong Kong": 30, "Istanbul": 24, "Singapore": 28, "Marrakech": 28, "New York": 23, "Havana": 28, "Mexico City": 16, "Rome": 27, "Lisbon": 24, "Oslo": 24, "Riga": 24, "Dublin": 25, "Hanoi": 32, "Miami": 29, "Lima": 18, "Vienna": 23, "Santiago": 10, "Johannesburg": 23, "Bangkok": 28, "Barcelona": 29, "Paris": 27, "Osaka": 25, "San Francisco": 13, "Bangalore": 24, "Jakarta": 27, "Stockholm": 29, "Prague": 16, "Sydney": 8, "Tehran": 37, "Buenos Aires": 14, "Madrid": 31, "Bogota": 14, "Dallas": 27, "Tokyo": 25, "Monterrey": 24, "Kyoto": 26, "Seattle": 12, "Brasilia": 25, "Chicago": 24}