{"Toronto": 24, "Bangkok": 26, "Buenos Aires": 11, "Sydney": 7, "Rome": 26, "Kyoto": 22, "Oslo": 21, "Cape Town": 9, "Moscow": 19, "Madrid": 30, "Valencia": 26, "Singapore": 28, "Brasilia": 27, "Bangalore": 22, "Tehran": 31, "Lisbon": 23, "Seattle": 22, "Santiago": 14, "New York": 27, "Jakarta": 24, "Amsterdam": 19, "Atlanta": 31, "Berlin": 22, "Brussels": 25, "London": 27, "Munich": 18, "Prague": 19, "Lima": 20, "Chicago": 24, "Vilnius": 20, "Lagos": 26, "Johannesburg": 12, "Vienna": 20, "Marrakech": 36, "Osaka": 26, "Dublin": 21, "Mexico City": 22, "Cairo": 31, "Caracas": 30, "Istanbul": 25, "Miami": 32, "Beijing": 25, "Hanoi": 30, "Riga": 17, "Havana": 30, "Monterrey": 30, "Hong Kong": 29, "Paris": 26, "Zurich": 18, "Barcelona": 26, "Mumbai": 29, "Dallas": 36, "San Francisco": 26, "Kuala Lumpur": 26, "Helsinki": 18, "Stockholm": 21, "Rio De Janeiro": 27, "Warsaw": 21, "Seoul": 21, "Tokyo": 21, "Bogota": 18}