{"Osaka": 30, "Cape Town": 7, "Warsaw": 18, "Berlin": 15, "Mumbai": 25, "Chicago": 22, "Cairo": 27, "Madrid": 22, "Havana": 24, "Bogota": 11, "Lagos": 25, "Amsterdam": 14, "Dallas": 32, "Tehran": 28, "Seattle": 23, "Brussels": 16, "Toronto": 21, "Singapore": 29, "Santiago": 10, "London": 17, "Dublin": 12, "Bangkok": 31, "Oslo": 13, "Brasilia": 25, "Helsinki": 14, "Barcelona": 22, "Mexico City": 16, "Caracas": 25, "Buenos Aires": 11, "Hong Kong": 31, "Stockholm": 12, "Kuala Lumpur": 27, "Zurich": 16, "Valencia": 22, "Beijing": 26, "Rome": 21, "Seoul": 24, "Marrakech": 23, "Johannesburg": -2, "Lima": 12, "Kyoto": 30, "Vienna": 18, "Hanoi": 29, "Vilnius": 14, "Riga": 15, "Prague": 17, "New York": 19, "Miami": 28, "Rio De Janeiro": 21, "Sydney": 18, "Paris": 18, "Lisbon": 19, "San Francisco": 26, "Moscow": 15, "Bangalore": 22, "Atlanta": 24, "Jakarta": 30, "Monterrey": 22, "Munich": 13, "Istanbul": 22, "Tokyo": 30}