{"Toronto": 29, "Mexico City": 22, "Buenos Aires": 16, "Moscow": 20, "Hong Kong": 29, "Monterrey": 31, "Istanbul": 21, "Rio De Janeiro": 26, "Oslo": 20, "Johannesburg": 10, "Miami": 28, "Hanoi": 27, "Stockholm": 15, "Seattle": 18, "Seoul": 22, "Riga": 15, "Helsinki": 17, "Tehran": 31, "Cape Town": 10, "Atlanta": 22, "New York": 28, "San Francisco": 23, "Valencia": 25, "Kyoto": 26, "Caracas": 28, "Cairo": 28, "Marrakech": 26, "Havana": 29, "Jakarta": 25, "Lisbon": 20, "Bogota": 16, "Santiago": 15, "Berlin": 21, "Amsterdam": 19, "Brussels": 21, "Paris": 22, "Rome": 21, "London": 19, "Singapore": 27, "Mumbai": 28, "Warsaw": 23, "Lagos": 26, "Sydney": 5, "Dallas": 38, "Bangkok": 26, "Kuala Lumpur": 26, "Barcelona": 21, "Madrid": 27, "Dublin": 22, "Osaka": 26, "Vilnius": 20, "Chicago": 30, "Brasilia": 26, "Vienna": 20, "Zurich": 18, "Prague": 18, "Beijing": 20, "Lima": 19, "Munich": 15, "Tokyo": 26, "Bangalore": 22}