{"Sydney": 10, "Barcelona": 27, "Kuala Lumpur": 27, "Rome": 28, "Seoul": 22, "Vilnius": 22, "Madrid": 31, "Lisbon": 26, "Berlin": 22, "London": 29, "Seattle": 20, "Toronto": 23, "Warsaw": 26, "Brussels": 27, "Lima": 21, "Helsinki": 11, "Valencia": 29, "Singapore": 28, "Atlanta": 31, "Monterrey": 25, "Osaka": 26, "Bogota": 16, "Marrakech": 37, "Kyoto": 23, "Moscow": 23, "Vienna": 24, "Dublin": 23, "Amsterdam": 23, "Johannesburg": 13, "Miami": 31, "Hanoi": 31, "Jakarta": 26, "Lagos": 29, "Tehran": 36, "Tokyo": 20, "Cairo": 35, "Munich": 19, "Zurich": 20, "Stockholm": 24, "Brasilia": 28, "Bangkok": 26, "Havana": 31, "Chicago": 23, "Buenos Aires": 11, "Prague": 23, "Dallas": 33, "Paris": 29, "Mumbai": 29, "Mexico City": 20, "Hong Kong": 30, "Rio De Janeiro": 27, "Beijing": 26, "Oslo": 22, "New York": 26, "Riga": 18, "Caracas": 29, "Santiago": 13, "San Francisco": 21, "Istanbul": 28, "Bangalore": 24, "Cape Town": 17}