{"Buenos Aires": 12, "Beijing": 30, "Hanoi": 37, "Amsterdam": 25, "Johannesburg": 19, "Madrid": 25, "Valencia": 35, "Cairo": 33, "Toronto": 27, "Miami": 28, "Stockholm": 20, "Berlin": 21, "New York": 27, "Kuala Lumpur": 28, "Barcelona": 29, "Paris": 27, "Bogota": 10, "Chicago": 22, "Sydney": 12, "Istanbul": 30, "Zurich": 27, "London": 28, "Atlanta": 24, "Bangkok": 26, "Lima": 11, "Cape Town": 9, "Moscow": 22, "Brasilia": 24, "Marrakech": 28, "Dallas": 26, "Hong Kong": 30, "Tokyo": 28, "Vienna": 23, "Lisbon": 21, "Caracas": 27, "Brussels": 27, "Havana": 21, "Seoul": 24, "Rio De Janeiro": 21, "Santiago": 4, "Mumbai": 27, "Oslo": 25, "Helsinki": 14, "Warsaw": 13, "Riga": 13, "Tehran": 39, "Kyoto": 27, "Monterrey": 23, "Lagos": 27, "Rome": 30, "Osaka": 27, "San Francisco": 15, "Bangalore": 29, "Mexico City": 11, "Singapore": 28, "Dublin": 21, "Prague": 21, "Seattle": 12, "Munich": 22, "Jakarta": 30, "Vilnius": 12}